{
  "O": 0,
  "B-art-broadcastprogram": 1,
  "I-art-broadcastprogram": 2,
  "B-art-film": 3,
  "I-art-film": 4,
  "B-art-music": 5,
  "I-art-music": 6,
  "B-art-other": 7,
  "I-art-other": 8,
  "B-art-painting": 9,
  "I-art-painting": 10,
  "B-art-writtenart": 11,
  "I-art-writtenart": 12,
  "B-building-airport": 13,
  "I-building-airport": 14,
  "B-building-hospital": 15,
  "I-building-hospital": 16,
  "B-building-hotel": 17,
  "I-building-hotel": 18,
  "B-building-library": 19,
  "I-building-library": 20,
  "B-building-other": 21,
  "I-building-other": 22,
  "B-building-restaurant": 23,
  "I-building-restaurant": 24,
  "B-building-sportsfacility": 25,
  "I-building-sportsfacility": 26,
  "B-building-theater": 27,
  "I-building-theater": 28,
  "B-event-attack/battle/war/militaryconflict": 29,
  "I-event-attack/battle/war/militaryconflict": 30,
  "B-event-disaster": 31,
  "I-event-disaster": 32,
  "B-event-election": 33,
  "I-event-election": 34,
  "B-event-other": 35,
  "I-event-other": 36,
  "B-event-protest": 37,
  "I-event-protest": 38,
  "B-event-sportsevent": 39,
  "I-event-sportsevent": 40,
  "B-location-GPE": 41,
  "I-location-GPE": 42,
  "B-location-bodiesofwater": 43,
  "I-location-bodiesofwater": 44,
  "B-location-island": 45,
  "I-location-island": 46,
  "B-location-mountain": 47,
  "I-location-mountain": 48,
  "B-location-other": 49,
  "I-location-other": 50,
  "B-location-park": 51,
  "I-location-park": 52,
  "B-location-road/railway/highway/transit": 53,
  "I-location-road/railway/highway/transit": 54,
  "B-organization-company": 55,
  "I-organization-company": 56,
  "B-organization-education": 57,
  "I-organization-education": 58,
  "B-organization-government/governmentagency": 59,
  "I-organization-government/governmentagency": 60,
  "B-organization-media/newspaper": 61,
  "I-organization-media/newspaper": 62,
  "B-organization-other": 63,
  "I-organization-other": 64,
  "B-organization-politicalparty": 65,
  "I-organization-politicalparty": 66,
  "B-organization-religion": 67,
  "I-organization-religion": 68,
  "B-organization-showorganization": 69,
  "I-organization-showorganization": 70,
  "B-organization-sportsleague": 71,
  "I-organization-sportsleague": 72,
  "B-organization-sportsteam": 73,
  "I-organization-sportsteam": 74,
  "B-other-astronomything": 75,
  "I-other-astronomything": 76,
  "B-other-award": 77,
  "I-other-award": 78,
  "B-other-biologything": 79,
  "I-other-biologything": 80,
  "B-other-chemicalthing": 81,
  "I-other-chemicalthing": 82,
  "B-other-currency": 83,
  "I-other-currency": 84,
  "B-other-disease": 85,
  "I-other-disease": 86,
  "B-other-educationaldegree": 87,
  "I-other-educationaldegree": 88,
  "B-other-god": 89,
  "I-other-god": 90,
  "B-other-language": 91,
  "I-other-language": 92,
  "B-other-law": 93,
  "I-other-law": 94,
  "B-other-livingthing": 95,
  "I-other-livingthing": 96,
  "B-other-medical": 97,
  "I-other-medical": 98,
  "B-person-actor": 99,
  "I-person-actor": 100,
  "B-person-artist/author": 101,
  "I-person-artist/author": 102,
  "B-person-athlete": 103,
  "I-person-athlete": 104,
  "B-person-director": 105,
  "I-person-director": 106,
  "B-person-other": 107,
  "I-person-other": 108,
  "B-person-politician": 109,
  "I-person-politician": 110,
  "B-person-scholar": 111,
  "I-person-scholar": 112,
  "B-person-soldier": 113,
  "I-person-soldier": 114,
  "B-product-airplane": 115,
  "I-product-airplane": 116,
  "B-product-car": 117,
  "I-product-car": 118,
  "B-product-food": 119,
  "I-product-food": 120,
  "B-product-game": 121,
  "I-product-game": 122,
  "B-product-other": 123,
  "I-product-other": 124,
  "B-product-ship": 125,
  "I-product-ship": 126,
  "B-product-software": 127,
  "I-product-software": 128,
  "B-product-train": 129,
  "I-product-train": 130,
  "B-product-weapon": 131,
  "I-product-weapon": 132
}